LICENSE
saucenaopie/__init__.py
saucenaopie/client/__init__.py
saucenaopie/client/asyncio.py
saucenaopie/client/base.py
saucenaopie/client/sync.py
saucenaopie/exceptions.py
saucenaopie/helper.py
saucenaopie/types/__init__.py
saucenaopie/types/account.py
saucenaopie/types/response.py
saucenaopie/types/result.py
saucenaopie/types/sauce.py
saucenaopie-1.3.3.dist-info/LICENSE
saucenaopie-1.3.3.dist-info/WHEEL
saucenaopie-1.3.3.dist-info/METADATA
saucenaopie-1.3.3.dist-info/RECORD
