Metadata-Version: 2.1
Name: saucenaopie
Version: 1.3.3
Summary: Modern and easy-to-use Python implementation for the SauceNao API, with Pydantic and full asyncio support.
Home-page: https://github.com/WhiteMemory99/saucenaopie
License: MIT
Keywords: saucenao
Author: WhiteMemory99
Author-email: lisen1510@gmail.com
Requires-Python: >=3.8,<4.0
Classifier: Intended Audience :: Developers
Classifier: License :: OSI Approved :: MIT License
Classifier: Operating System :: OS Independent
Classifier: Programming Language :: Python :: 3
Classifier: Programming Language :: Python :: 3.10
Classifier: Programming Language :: Python :: 3.8
Classifier: Programming Language :: Python :: 3.9
Classifier: Topic :: Software Development :: Libraries :: Application Frameworks
Requires-Dist: httpx (>=0.22.0,<0.23.0)
Requires-Dist: pydantic (>=1.9.0,<2.0.0)
Project-URL: Repository, https://github.com/WhiteMemory99/saucenaopie
